vktop/__init__.py
vktop/__main__.py
vktop/argparser.py
vktop/constants.py
vktop/post.py
vktop/utils.py
vktop-2.4.dist-info/METADATA
vktop-2.4.dist-info/RECORD
vktop-2.4.dist-info/WHEEL
vktop-2.4.dist-info/entry_points.txt
vktop-2.4.dist-info/top_level.txt
