Metadata-Version: 2.1
Name: vktop
Version: 2.4
Summary: VK-Top is used for getting popular posts of any public available page at VK.com
Home-page: https://github.com/yutkin/VK-Top
Author: Dmitry Yutkin
Author-email: yutkinn@gmail.com
License: MIT
Download-URL: https://github.com/yutkin/VK-Top/tarball/2.4
Keywords: vk.com,vk,downloader,posts,social,networks,likes,reposts
Platform: UNKNOWN
Classifier: Development Status :: 5 - Production/Stable
Classifier: Intended Audience :: End Users/Desktop
Classifier: License :: OSI Approved :: MIT License
Classifier: Operating System :: MacOS
Classifier: Operating System :: Unix
Classifier: Operating System :: Microsoft
Classifier: Programming Language :: Python :: 3
Classifier: Programming Language :: Python :: 2
Classifier: Topic :: Internet
Classifier: Topic :: Utilities
Requires-Dist: requests
